xtea4/__init__.py
xtea4/counter.py
xtea4-0.6.1.dist-info/METADATA
xtea4-0.6.1.dist-info/WHEEL
xtea4-0.6.1.dist-info/top_level.txt
xtea4-0.6.1.dist-info/RECORD
