Metadata-Version: 2.1
Name: xtea4
Version: 0.6.1
Summary: A python version of XTEA
Home-page: https://github.com/tgates42/xtea/wiki
Author: Simon Biewald
Author-email: simon.biewald@hotmail.de
License: Public Domain
Download-URL: https://github.com/tgates42/xtea
Keywords: xtea tea encryption crypt
Platform: UNKNOWN
Classifier: Development Status :: 4 - Beta
Classifier: License :: Public Domain
Classifier: Operating System :: OS Independent
Classifier: Programming Language :: Python :: 2
Classifier: Programming Language :: Python :: 2.7
Classifier: Programming Language :: Python :: 3
Classifier: Programming Language :: Python :: 3.3
Classifier: Programming Language :: Python :: 3.4
Classifier: Programming Language :: Python :: 3.5
Classifier: Programming Language :: Python :: 3.6
Classifier: Programming Language :: Python :: 3.7
Classifier: Programming Language :: Python :: Implementation :: CPython
Classifier: Programming Language :: Python :: Implementation :: PyPy
Classifier: Topic :: Security
Classifier: Topic :: Security :: Cryptography
Requires-Dist: pep272-encryption
